nimbusagent/__init__.py
nimbusagent/agent/__init__.py
nimbusagent/agent/base.py
nimbusagent/agent/completion.py
nimbusagent/agent/streaming.py
nimbusagent/functions/__init__.py
nimbusagent/functions/handler.py
nimbusagent/functions/parser.py
nimbusagent/functions/responses.py
nimbusagent/memory/__init__.py
nimbusagent/memory/base.py
nimbusagent/utils/__init__.py
nimbusagent/utils/helper.py
nimbusagent-0.8.0.dist-info/licenses/LICENSE.txt
nimbusagent-0.8.0.dist-info/METADATA
nimbusagent-0.8.0.dist-info/WHEEL
nimbusagent-0.8.0.dist-info/top_level.txt
nimbusagent-0.8.0.dist-info/RECORD
