Metadata-Version: 2.4
Name: nimbusagent
Version: 0.8.0
Summary: An OpenAI agent with basic memory, functions, and moderation support
Author: Lee Huffman
License: MIT License
Project-URL: homepage, https://github.com/aerisweather/nimbusagent
Project-URL: repository, https://github.com/aerisweather/nimbusagent
Keywords: openai,gpt3,gpt3.5,gpt4,gpt4o,ai
Classifier: Development Status :: 5 - Production/Stable
Classifier: Intended Audience :: Developers
Classifier: License :: OSI Approved :: MIT License
Classifier: Programming Language :: Python :: 3
Classifier: Programming Language :: Python :: 3.8
Classifier: Programming Language :: Python :: 3.9
Classifier: Programming Language :: Python :: 3.10
Classifier: Programming Language :: Python :: 3.11
Classifier: Programming Language :: Python :: 3.12
Classifier: Operating System :: OS Independent
Classifier: Operating System :: POSIX
Classifier: Operating System :: MacOS
Classifier: Operating System :: POSIX :: Linux
Classifier: Operating System :: Microsoft :: Windows
Classifier: Topic :: Software Development :: Libraries :: Python Modules
Requires-Python: >=3.10
License-File: LICENSE.txt
Requires-Dist: openai>=1.99.1
Requires-Dist: tiktoken==0.10.0
Requires-Dist: pydantic==2.11.7
Requires-Dist: numpy==2.3.2
Requires-Dist: dotenv==0.9.9
Provides-Extra: dev
Requires-Dist: pytest~=8.4.1; extra == "dev"
Requires-Dist: black~=25.8.0; extra == "dev"
Requires-Dist: mypy~=1.17.1; extra == "dev"
Requires-Dist: types-requests~=2.32.4; extra == "dev"
Dynamic: license-file
